{
 "custom_fields": [
  {
   "_assign": null,
   "_comments": null,
   "_liked_by": null,
   "_user_tags": null,
   "allow_in_quick_entry": 0,
   "allow_on_submit": 0,
   "bold": 0,
   "collapsible": 0,
   "collapsible_depends_on": null,
   "columns": 0,
   "creation": "2020-02-17 03:13:54.365009",
   "default": "Today",
   "depends_on": null,
   "description": null,
   "docstatus": 0,
   "dt": "Customer",
   "fetch_from": null,
   "fetch_if_empty": 0,
   "fieldname": "opening_date",
   "fieldtype": "Date",
   "hidden": 0,
   "idx": 9,
   "ignore_user_permissions": 0,
   "ignore_xss_filter": 0,
   "in_global_search": 0,
   "in_list_view": 0,
   "in_standard_filter": 0,
   "insert_after": "lead_name",
   "label": "Opening Date",
   "length": 0,
   "modified": "2020-02-17 03:13:54.365009",
   "modified_by": "Administrator",
   "name": "Customer-opening_date",
   "no_copy": 0,
   "options": null,
   "owner": "Administrator",
   "parent": null,
   "parentfield": null,
   "parenttype": null,
   "permlevel": 0,
   "precision": "",
   "print_hide": 0,
   "print_hide_if_no_value": 0,
   "print_width": null,
   "read_only": 0,
   "report_hide": 0,
   "reqd": 0,
   "search_index": 0,
   "translatable": 0,
   "unique": 0,
   "width": null
  },
  {
   "_assign": null,
   "_comments": null,
   "_liked_by": null,
   "_user_tags": null,
   "allow_in_quick_entry": 0,
   "allow_on_submit": 0,
   "bold": 0,
   "collapsible": 0,
   "collapsible_depends_on": null,
   "columns": 0,
   "creation": "2020-05-18 02:29:17.306334",
   "default": null,
   "depends_on": "",
   "description": null,
   "docstatus": 0,
   "dt": "Customer",
   "fetch_from": null,
   "fetch_if_empty": 0,
   "fieldname": "licenses",
   "fieldtype": "Table",
   "hidden": 0,
   "idx": 28,
   "ignore_user_permissions": 0,
   "ignore_xss_filter": 0,
   "in_global_search": 0,
   "in_list_view": 0,
   "in_standard_filter": 0,
   "insert_after": "licenses_sb",
   "label": "Licenses",
   "length": 0,
   "modified": "2020-05-18 02:29:17.306334",
   "modified_by": "Administrator",
   "name": "Customer-licenses",
   "no_copy": 0,
   "options": "Compliance License Detail",
   "owner": "Administrator",
   "parent": null,
   "parentfield": null,
   "parenttype": null,
   "permlevel": 0,
   "precision": "",
   "print_hide": 0,
   "print_hide_if_no_value": 0,
   "print_width": null,
   "read_only": 0,
   "report_hide": 0,
   "reqd": 0,
   "search_index": 0,
   "translatable": 0,
   "unique": 0,
   "width": null
  },
  {
   "_assign": null,
   "_comments": null,
   "_liked_by": null,
   "_user_tags": null,
   "allow_in_quick_entry": 0,
   "allow_on_submit": 0,
   "bold": 0,
   "collapsible": 0,
   "collapsible_depends_on": null,
   "columns": 0,
   "creation": "2020-05-18 02:30:07.693030",
   "default": null,
   "depends_on": null,
   "description": null,
   "docstatus": 0,
   "dt": "Customer",
   "fetch_from": null,
   "fetch_if_empty": 0,
   "fieldname": "licenses_sb",
   "fieldtype": "Section Break",
   "hidden": 0,
   "idx": 27,
   "ignore_user_permissions": 0,
   "ignore_xss_filter": 0,
   "in_global_search": 0,
   "in_list_view": 0,
   "in_standard_filter": 0,
   "insert_after": "language",
   "label": "Licenses",
   "length": 0,
   "modified": "2020-05-18 02:30:07.693030",
   "modified_by": "Administrator",
   "name": "Customer-licenses_sb",
   "no_copy": 0,
   "options": null,
   "owner": "Administrator",
   "parent": null,
   "parentfield": null,
   "parenttype": null,
   "permlevel": 0,
   "precision": "",
   "print_hide": 0,
   "print_hide_if_no_value": 0,
   "print_width": null,
   "read_only": 0,
   "report_hide": 0,
   "reqd": 0,
   "search_index": 0,
   "translatable": 0,
   "unique": 0,
   "width": null
  }
 ],
 "custom_perms": [],
 "doctype": "Customer",
 "property_setters": [
  {
   "_assign": null,
   "_comments": null,
   "_liked_by": null,
   "_user_tags": null,
   "creation": "2020-07-08 04:36:58.392390",
   "default_value": null,
   "doc_type": "Customer",
   "docstatus": 0,
   "doctype_or_field": "DocField",
   "field_name": "customer_type",
   "idx": 0,
   "modified": "2020-07-08 04:36:58.392390",
   "modified_by": "Administrator",
   "name": "Customer-customer_type-options",
   "owner": "Administrator",
   "parent": null,
   "parentfield": null,
   "parenttype": null,
   "property": "options",
   "property_type": "Text",
   "value": "Company\nIndividual\nCorporation\nLLC"
  },
  {
   "_assign": null,
   "_comments": null,
   "_liked_by": null,
   "_user_tags": null,
   "creation": "2020-06-11 02:15:14.903233",
   "default_value": null,
   "doc_type": "Customer",
   "docstatus": 0,
   "doctype_or_field": "DocField",
   "field_name": "gender",
   "idx": 0,
   "modified": "2020-06-11 02:15:14.903233",
   "modified_by": "Administrator",
   "name": "Customer-gender-hidden",
   "owner": "Administrator",
   "parent": null,
   "parentfield": null,
   "parenttype": null,
   "property": "hidden",
   "property_type": "Check",
   "value": "1"
  },
  {
   "_assign": null,
   "_comments": null,
   "_liked_by": null,
   "_user_tags": null,
   "creation": "2020-01-16 02:48:12.781242",
   "default_value": null,
   "doc_type": "Customer",
   "docstatus": 0,
   "doctype_or_field": "DocField",
   "field_name": "naming_series",
   "idx": 0,
   "modified": "2020-01-16 02:48:12.781242",
   "modified_by": "Administrator",
   "name": "Customer-naming_series-options",
   "owner": "Administrator",
   "parent": null,
   "parentfield": null,
   "parenttype": null,
   "property": "options",
   "property_type": "Text",
   "value": "CUST-.YYYY.-"
  },
  {
   "_assign": null,
   "_comments": null,
   "_liked_by": null,
   "_user_tags": null,
   "creation": "2019-12-17 14:22:35.579786",
   "default_value": null,
   "doc_type": "Customer",
   "docstatus": 0,
   "doctype_or_field": "DocField",
   "field_name": "naming_series",
   "idx": 0,
   "modified": "2019-12-17 14:22:35.579786",
   "modified_by": "matt@bloomstack.com",
   "name": "Customer-naming_series-hidden",
   "owner": "matt@bloomstack.com",
   "parent": null,
   "parentfield": null,
   "parenttype": null,
   "property": "hidden",
   "property_type": "Check",
   "value": "1"
  },
  {
   "_assign": null,
   "_comments": null,
   "_liked_by": null,
   "_user_tags": null,
   "creation": "2019-12-17 14:22:35.436424",
   "default_value": null,
   "doc_type": "Customer",
   "docstatus": 0,
   "doctype_or_field": "DocField",
   "field_name": "naming_series",
   "idx": 0,
   "modified": "2019-12-17 14:22:35.436424",
   "modified_by": "matt@bloomstack.com",
   "name": "Customer-naming_series-reqd",
   "owner": "matt@bloomstack.com",
   "parent": null,
   "parentfield": null,
   "parenttype": null,
   "property": "reqd",
   "property_type": "Check",
   "value": "0"
  }
 ],
 "sync_on_migrate": 1
}